{"cameraMode":{"drawMode":0,"name":"Shaded","section":"Shading Mode"},"sceneLighting":true,"audioPlay":false,"sceneViewState":{"showFog":true,"showMaterialUpdate":false,"showSkybox":true,"showFlares":true,"showImageEffects":true,"showParticleSystems":true},"in2DMode":false,"pivot":{"x":302.96636962890627,"y":259.9203186035156,"z":-26.674100875854493},"rotation":{"x":-0.0707504004240036,"y":0.0020917817018926145,"z":-0.00014844695397187024,"w":-0.9974918365478516},"size":499.2272644042969,"orthographic":false}